t9text/__init__.py
t9text/t9.py
t9text-0.1.0.dist-info/LICENSE
t9text-0.1.0.dist-info/METADATA
t9text-0.1.0.dist-info/WHEEL
t9text-0.1.0.dist-info/top_level.txt
t9text-0.1.0.dist-info/RECORD
