Metadata-Version: 2.1
Name: t9text
Version: 0.1.0
Summary: A package for handling T9 text message key mapping
Home-page: https://github.com/bxbrenden/t9text
Author: Brenden Hyde
Author-email: brendenahyde@gmail.com
License: UNKNOWN
Platform: UNKNOWN
Classifier: Programming Language :: Python :: 3
Classifier: License :: OSI Approved :: GNU Affero General Public License v3
Classifier: Operating System :: OS Independent
Requires-Python: >=3.8
